{"id":200,"name":"Spawn","kind":128,"kindString":"Class","flags":{},"comment":{"summary":[{"kind":"text","text":"### Creates spawned processes.\n- the tsc compiler in watch mode\n- disposable typedoc processes"}]},"children":[{"id":201,"name":"constructor","kind":512,"kindString":"Constructor","flags":{"isOverride":true},"sources":[{"fileName":"src/lib/Spawn.ts","fullFileName":"/home/runner/work/typedoc-plugin-hot-dev/typedoc-plugin-hot-dev/src/lib/Spawn.ts","line":19,"character":1,"url":"https://github.com/citkane/typedoc-plugin-hot-dev/blob/83cd4be/src/lib/Spawn.ts#L19"}],"signatures":[{"id":202,"name":"constructor","kind":16384,"kindString":"Constructor signature","flags":{"isOverride":true},"parameters":[{"id":203,"name":"emitter","kind":32768,"kindString":"Parameter","flags":{},"type":{"type":"reference","id":49,"name":"HotEmitter"},"text":{}}],"type":{"type":"reference","id":200,"name":"Spawn"},"overwrites":{"type":"reference","id":272,"name":"HotUtils.constructor"},"is":{"declaration":false},"location":{"query":"lib/Spawn.Spawn.Constructor.constructor","hash":"constructor.new Spawn"},"text":{},"sources":[{"fileName":"src/lib/Spawn.ts","fullFileName":"/home/runner/work/typedoc-plugin-hot-dev/typedoc-plugin-hot-dev/src/lib/Spawn.ts","line":19,"character":1,"url":"https://github.com/citkane/typedoc-plugin-hot-dev/blob/83cd4be/src/lib/Spawn.ts#L19"}],"parentId":201}],"overwrites":{"type":"reference","id":271,"name":"HotUtils.constructor"},"is":{"declaration":true},"location":{"query":"lib/Spawn.Class.Spawn","hash":"constructor"},"text":{},"parentId":200},{"id":204,"name":"emitter","kind":1024,"kindString":"Property","flags":{"isOverride":true},"sources":[{"fileName":"src/lib/Spawn.ts","fullFileName":"/home/runner/work/typedoc-plugin-hot-dev/typedoc-plugin-hot-dev/src/lib/Spawn.ts","line":18,"character":1,"url":"https://github.com/citkane/typedoc-plugin-hot-dev/blob/83cd4be/src/lib/Spawn.ts#L18"}],"type":{"type":"reference","id":49,"name":"HotEmitter"},"overwrites":{"type":"reference","id":274,"name":"HotUtils.emitter"},"is":{"declaration":true},"location":{"query":"lib/Spawn.Class.Spawn","hash":"emitter"},"text":{},"parentId":200},{"id":240,"name":"isReady","kind":1024,"kindString":"Property","flags":{"isInherited":true},"sources":[{"fileName":"src/lib/Utils.ts","fullFileName":"/home/runner/work/typedoc-plugin-hot-dev/typedoc-plugin-hot-dev/src/lib/Utils.ts","line":12,"character":1,"url":"https://github.com/citkane/typedoc-plugin-hot-dev/blob/83cd4be/src/lib/Utils.ts#L12"}],"type":{"type":"intrinsic","name":"boolean"},"inheritedFrom":{"type":"reference","id":275,"name":"HotUtils.isReady"},"is":{"declaration":true},"location":{"query":"lib/Spawn.Class.Spawn","hash":"isReady"},"text":{},"parentId":200},{"id":241,"name":"timer","kind":1024,"kindString":"Property","flags":{"isInherited":true},"sources":[{"fileName":"src/lib/Utils.ts","fullFileName":"/home/runner/work/typedoc-plugin-hot-dev/typedoc-plugin-hot-dev/src/lib/Utils.ts","line":13,"character":1,"url":"https://github.com/citkane/typedoc-plugin-hot-dev/blob/83cd4be/src/lib/Utils.ts#L13"}],"type":{"type":"intrinsic","name":"any"},"inheritedFrom":{"type":"reference","id":276,"name":"HotUtils.timer"},"is":{"declaration":true},"location":{"query":"lib/Spawn.Class.Spawn","hash":"timer"},"text":{},"parentId":200},{"id":253,"name":"debounceWatchCallBack","kind":2048,"kindString":"Method","flags":{"isProtected":true,"isInherited":true},"sources":[{"fileName":"src/lib/Utils.ts","fullFileName":"/home/runner/work/typedoc-plugin-hot-dev/typedoc-plugin-hot-dev/src/lib/Utils.ts","line":87,"character":11,"url":"https://github.com/citkane/typedoc-plugin-hot-dev/blob/83cd4be/src/lib/Utils.ts#L87"}],"signatures":[{"id":254,"name":"debounceWatchCallBack","kind":4096,"kindString":"Call signature","flags":{"isInherited":true},"parameters":[{"id":255,"name":"path","kind":32768,"kindString":"Parameter","flags":{},"type":{"type":"intrinsic","name":"any"},"text":{}},{"id":256,"name":"emitter","kind":32768,"kindString":"Parameter","flags":{},"type":{"type":"reference","id":49,"name":"HotEmitter"},"text":{}}],"type":{"type":"intrinsic","name":"void"},"inheritedFrom":{"type":"reference","id":289,"name":"HotUtils.debounceWatchCallBack"},"is":{"declaration":false},"location":{"query":"lib/Spawn.Spawn.Method.debounceWatchCallBack","hash":"debounceWatchCallBack.debounceWatchCallBack"},"text":{},"sources":[{"fileName":"src/lib/Utils.ts","fullFileName":"/home/runner/work/typedoc-plugin-hot-dev/typedoc-plugin-hot-dev/src/lib/Utils.ts","line":87,"character":1,"url":"https://github.com/citkane/typedoc-plugin-hot-dev/blob/83cd4be/src/lib/Utils.ts#L87"}],"parentId":253}],"inheritedFrom":{"type":"reference","id":288,"name":"HotUtils.debounceWatchCallBack"},"is":{"declaration":true},"location":{"query":"lib/Spawn.Class.Spawn","hash":"debounceWatchCallBack"},"text":{},"parentId":200},{"id":220,"name":"emitBuildStatus","kind":2048,"kindString":"Method","flags":{"isPrivate":true},"sources":[{"fileName":"src/lib/Spawn.ts","fullFileName":"/home/runner/work/typedoc-plugin-hot-dev/typedoc-plugin-hot-dev/src/lib/Spawn.ts","line":133,"character":9,"url":"https://github.com/citkane/typedoc-plugin-hot-dev/blob/83cd4be/src/lib/Spawn.ts#L133"}],"signatures":[{"id":221,"name":"emitBuildStatus","kind":4096,"kindString":"Call signature","flags":{},"parameters":[{"id":222,"name":"kind","kind":32768,"kindString":"Parameter","flags":{},"type":{"type":"union","types":[{"type":"literal","value":"init"},{"type":"literal","value":"refreshed"}]},"text":{}},{"id":223,"name":"docPath","kind":32768,"kindString":"Parameter","flags":{},"type":{"type":"intrinsic","name":"string"},"text":{}},{"id":224,"name":"emitter","kind":32768,"kindString":"Parameter","flags":{},"type":{"type":"reference","id":49,"name":"HotEmitter"},"text":{}}],"type":{"type":"intrinsic","name":"any"},"is":{"declaration":false},"location":{"query":"lib/Spawn.Spawn.Method.emitBuildStatus","hash":"emitBuildStatus.emitBuildStatus"},"text":{},"sources":[{"fileName":"src/lib/Spawn.ts","fullFileName":"/home/runner/work/typedoc-plugin-hot-dev/typedoc-plugin-hot-dev/src/lib/Spawn.ts","line":133,"character":27,"url":"https://github.com/citkane/typedoc-plugin-hot-dev/blob/83cd4be/src/lib/Spawn.ts#L133"}],"parentId":220}],"is":{"declaration":true},"location":{"query":"lib/Spawn.Class.Spawn","hash":"emitBuildStatus"},"text":{},"parentId":200},{"id":257,"name":"findJsonInString","kind":2048,"kindString":"Method","flags":{"isProtected":true,"isInherited":true},"sources":[{"fileName":"src/lib/Utils.ts","fullFileName":"/home/runner/work/typedoc-plugin-hot-dev/typedoc-plugin-hot-dev/src/lib/Utils.ts","line":94,"character":11,"url":"https://github.com/citkane/typedoc-plugin-hot-dev/blob/83cd4be/src/lib/Utils.ts#L94"}],"signatures":[{"id":258,"name":"findJsonInString","kind":4096,"kindString":"Call signature","flags":{"isInherited":true},"parameters":[{"id":259,"name":"string","kind":32768,"kindString":"Parameter","flags":{},"type":{"type":"intrinsic","name":"string"},"text":{}}],"type":{"type":"union","types":[{"type":"literal","value":false},{"type":"reflection","declaration":{"id":260,"name":"__type","kind":65536,"kindString":"Type literal","flags":{},"sources":[{"fileName":"src/lib/Utils.ts","line":96,"character":12,"url":"https://github.com/citkane/typedoc-plugin-hot-dev/blob/83cd4be/src/lib/Utils.ts#L96"}],"indexSignature":{"id":261,"name":"__index","kind":8192,"kindString":"Index signature","flags":{},"parameters":[{"id":262,"name":"key","kind":32768,"flags":{},"type":{"type":"intrinsic","name":"string"}}],"type":{"type":"intrinsic","name":"unknown"}}}}]},"inheritedFrom":{"type":"reference","id":293,"name":"HotUtils.findJsonInString"},"is":{"declaration":false},"location":{"query":"lib/Spawn.Spawn.Method.findJsonInString","hash":"findJsonInString.findJsonInString"},"text":{},"sources":[{"fileName":"src/lib/Utils.ts","fullFileName":"/home/runner/work/typedoc-plugin-hot-dev/typedoc-plugin-hot-dev/src/lib/Utils.ts","line":94,"character":1,"url":"https://github.com/citkane/typedoc-plugin-hot-dev/blob/83cd4be/src/lib/Utils.ts#L94"}],"parentId":257}],"inheritedFrom":{"type":"reference","id":292,"name":"HotUtils.findJsonInString"},"is":{"declaration":true},"location":{"query":"lib/Spawn.Class.Spawn","hash":"findJsonInString"},"text":{},"parentId":200},{"id":246,"name":"getHttpRoot","kind":2048,"kindString":"Method","flags":{"isProtected":true,"isInherited":true},"sources":[{"fileName":"src/lib/Utils.ts","fullFileName":"/home/runner/work/typedoc-plugin-hot-dev/typedoc-plugin-hot-dev/src/lib/Utils.ts","line":51,"character":11,"url":"https://github.com/citkane/typedoc-plugin-hot-dev/blob/83cd4be/src/lib/Utils.ts#L51"}],"signatures":[{"id":247,"name":"getHttpRoot","kind":4096,"kindString":"Call signature","flags":{"isInherited":true},"comment":{"summary":[{"kind":"text","text":"For compatibility with any other plugins which may override the 'out'\noption, we explicitly get it from 'typedoc.json'."}],"blockTags":[{"tag":"@returns","content":[]}]},"parameters":[{"id":248,"name":"opts","kind":32768,"kindString":"Parameter","flags":{},"type":{"type":"reference","id":19,"name":"allOptions"},"text":{}}],"type":{"type":"intrinsic","name":"string"},"inheritedFrom":{"type":"reference","id":282,"name":"HotUtils.getHttpRoot"},"is":{"declaration":false},"location":{"query":"lib/Spawn.Spawn.Method.getHttpRoot","hash":"getHttpRoot.getHttpRoot"},"text":{"comment":"<p>For compatibility with any other plugins which may override the &#39;out&#39;\noption, we explicitly get it from &#39;typedoc.json&#39;.</p>\n<h5>Returns:</h5>"},"sources":[{"fileName":"src/lib/Utils.ts","fullFileName":"/home/runner/work/typedoc-plugin-hot-dev/typedoc-plugin-hot-dev/src/lib/Utils.ts","line":51,"character":1,"url":"https://github.com/citkane/typedoc-plugin-hot-dev/blob/83cd4be/src/lib/Utils.ts#L51"}],"parentId":246}],"inheritedFrom":{"type":"reference","id":281,"name":"HotUtils.getHttpRoot"},"is":{"declaration":true},"location":{"query":"lib/Spawn.Class.Spawn","hash":"getHttpRoot"},"text":{},"parentId":200},{"id":225,"name":"getTdocOptions","kind":2048,"kindString":"Method","flags":{"isProtected":true},"sources":[{"fileName":"src/lib/Spawn.ts","fullFileName":"/home/runner/work/typedoc-plugin-hot-dev/typedoc-plugin-hot-dev/src/lib/Spawn.ts","line":147,"character":11,"url":"https://github.com/citkane/typedoc-plugin-hot-dev/blob/83cd4be/src/lib/Spawn.ts#L147"}],"signatures":[{"id":226,"name":"getTdocOptions","kind":4096,"kindString":"Call signature","flags":{},"parameters":[{"id":227,"name":"emitter","kind":32768,"kindString":"Parameter","flags":{},"type":{"type":"reference","id":49,"name":"HotEmitter"},"text":{}},{"id":228,"name":"opts","kind":32768,"kindString":"Parameter","flags":{},"type":{"type":"reference","id":19,"name":"allOptions"},"text":{}},{"id":229,"name":"controller","kind":32768,"kindString":"Parameter","flags":{},"type":{"type":"reference","name":"AbortController","qualifiedName":"AbortController","package":"typescript"},"text":{}},{"id":230,"name":"command","kind":32768,"kindString":"Parameter","flags":{},"type":{"type":"intrinsic","name":"string"},"defaultValue":"'node'","text":{}}],"type":{"type":"intrinsic","name":"void"},"is":{"declaration":false},"location":{"query":"lib/Spawn.Spawn.Method.getTdocOptions","hash":"getTdocOptions.getTdocOptions"},"text":{},"sources":[{"fileName":"src/lib/Spawn.ts","fullFileName":"/home/runner/work/typedoc-plugin-hot-dev/typedoc-plugin-hot-dev/src/lib/Spawn.ts","line":147,"character":1,"url":"https://github.com/citkane/typedoc-plugin-hot-dev/blob/83cd4be/src/lib/Spawn.ts#L147"}],"parentId":225}],"is":{"declaration":true},"location":{"query":"lib/Spawn.Class.Spawn","hash":"getTdocOptions"},"text":{},"parentId":200},{"id":210,"name":"getTscConfig","kind":2048,"kindString":"Method","flags":{"isProtected":true},"sources":[{"fileName":"src/lib/Spawn.ts","fullFileName":"/home/runner/work/typedoc-plugin-hot-dev/typedoc-plugin-hot-dev/src/lib/Spawn.ts","line":61,"character":11,"url":"https://github.com/citkane/typedoc-plugin-hot-dev/blob/83cd4be/src/lib/Spawn.ts#L61"}],"signatures":[{"id":211,"name":"getTscConfig","kind":4096,"kindString":"Call signature","flags":{},"parameters":[{"id":212,"name":"emitter","kind":32768,"kindString":"Parameter","flags":{},"type":{"type":"reference","id":49,"name":"HotEmitter"},"text":{}}],"type":{"type":"intrinsic","name":"void"},"is":{"declaration":false},"location":{"query":"lib/Spawn.Spawn.Method.getTscConfig","hash":"getTscConfig.getTscConfig"},"text":{},"sources":[{"fileName":"src/lib/Spawn.ts","fullFileName":"/home/runner/work/typedoc-plugin-hot-dev/typedoc-plugin-hot-dev/src/lib/Spawn.ts","line":61,"character":1,"url":"https://github.com/citkane/typedoc-plugin-hot-dev/blob/83cd4be/src/lib/Spawn.ts#L61"}],"parentId":210}],"is":{"declaration":true},"location":{"query":"lib/Spawn.Class.Spawn","hash":"getTscConfig"},"text":{},"parentId":200},{"id":263,"name":"logger","kind":2048,"kindString":"Method","flags":{"isProtected":true,"isInherited":true},"sources":[{"fileName":"src/lib/Utils.ts","fullFileName":"/home/runner/work/typedoc-plugin-hot-dev/typedoc-plugin-hot-dev/src/lib/Utils.ts","line":112,"character":11,"url":"https://github.com/citkane/typedoc-plugin-hot-dev/blob/83cd4be/src/lib/Utils.ts#L112"}],"signatures":[{"id":264,"name":"logger","kind":4096,"kindString":"Call signature","flags":{"isInherited":true},"parameters":[{"id":265,"name":"context","kind":32768,"kindString":"Parameter","flags":{},"type":{"type":"reference","id":45,"name":"logContexts"},"text":{}},{"id":266,"name":"message","kind":32768,"kindString":"Parameter","flags":{},"type":{"type":"intrinsic","name":"string"},"text":{}},{"id":267,"name":"type","kind":32768,"kindString":"Parameter","flags":{},"type":{"type":"union","types":[{"type":"literal","value":"error"},{"type":"literal","value":"warn"},{"type":"literal","value":"log"}]},"text":{}},{"id":268,"name":"prefix","kind":32768,"kindString":"Parameter","flags":{},"type":{"type":"intrinsic","name":"boolean"},"defaultValue":"false","text":{}}],"type":{"type":"intrinsic","name":"void"},"inheritedFrom":{"type":"reference","id":299,"name":"HotUtils.logger"},"is":{"declaration":false},"location":{"query":"lib/Spawn.Spawn.Method.logger","hash":"logger.logger"},"text":{},"sources":[{"fileName":"src/lib/Utils.ts","fullFileName":"/home/runner/work/typedoc-plugin-hot-dev/typedoc-plugin-hot-dev/src/lib/Utils.ts","line":112,"character":1,"url":"https://github.com/citkane/typedoc-plugin-hot-dev/blob/83cd4be/src/lib/Utils.ts#L112"}],"parentId":263}],"inheritedFrom":{"type":"reference","id":298,"name":"HotUtils.logger"},"is":{"declaration":true},"location":{"query":"lib/Spawn.Class.Spawn","hash":"logger"},"text":{},"parentId":200},{"id":242,"name":"parseOptions","kind":2048,"kindString":"Method","flags":{"isProtected":true,"isInherited":true},"sources":[{"fileName":"src/lib/Utils.ts","fullFileName":"/home/runner/work/typedoc-plugin-hot-dev/typedoc-plugin-hot-dev/src/lib/Utils.ts","line":20,"character":11,"url":"https://github.com/citkane/typedoc-plugin-hot-dev/blob/83cd4be/src/lib/Utils.ts#L20"}],"signatures":[{"id":243,"name":"parseOptions","kind":4096,"kindString":"Call signature","flags":{"isInherited":true},"parameters":[{"id":244,"name":"opts","kind":32768,"kindString":"Parameter","flags":{},"type":{"type":"reference","id":19,"name":"allOptions"},"text":{}},{"id":245,"name":"app","kind":32768,"kindString":"Parameter","flags":{},"type":{"type":"reference","name":"Application","qualifiedName":"Application","package":"typedoc"},"text":{}}],"type":{"type":"reference","id":19,"name":"allOptions"},"inheritedFrom":{"type":"reference","id":278,"name":"HotUtils.parseOptions"},"is":{"declaration":false},"location":{"query":"lib/Spawn.Spawn.Method.parseOptions","hash":"parseOptions.parseOptions"},"text":{},"sources":[{"fileName":"src/lib/Utils.ts","fullFileName":"/home/runner/work/typedoc-plugin-hot-dev/typedoc-plugin-hot-dev/src/lib/Utils.ts","line":20,"character":1,"url":"https://github.com/citkane/typedoc-plugin-hot-dev/blob/83cd4be/src/lib/Utils.ts#L20"}],"parentId":242}],"inheritedFrom":{"type":"reference","id":277,"name":"HotUtils.parseOptions"},"is":{"declaration":true},"location":{"query":"lib/Spawn.Class.Spawn","hash":"parseOptions"},"text":{},"parentId":200},{"id":236,"name":"runNpmScripts","kind":2048,"kindString":"Method","flags":{"isProtected":true},"sources":[{"fileName":"src/lib/Spawn.ts","fullFileName":"/home/runner/work/typedoc-plugin-hot-dev/typedoc-plugin-hot-dev/src/lib/Spawn.ts","line":201,"character":11,"url":"https://github.com/citkane/typedoc-plugin-hot-dev/blob/83cd4be/src/lib/Spawn.ts#L201"}],"signatures":[{"id":237,"name":"runNpmScripts","kind":4096,"kindString":"Call signature","flags":{},"parameters":[{"id":238,"name":"emitter","kind":32768,"kindString":"Parameter","flags":{},"type":{"type":"reference","id":49,"name":"HotEmitter"},"text":{}},{"id":239,"name":"opts","kind":32768,"kindString":"Parameter","flags":{},"type":{"type":"reference","id":19,"name":"allOptions"},"text":{}}],"type":{"type":"array","elementType":{"type":"reference","id":39,"name":"spawnedProcess"}},"is":{"declaration":false},"location":{"query":"lib/Spawn.Spawn.Method.runNpmScripts","hash":"runNpmScripts.runNpmScripts"},"text":{},"sources":[{"fileName":"src/lib/Spawn.ts","fullFileName":"/home/runner/work/typedoc-plugin-hot-dev/typedoc-plugin-hot-dev/src/lib/Spawn.ts","line":201,"character":1,"url":"https://github.com/citkane/typedoc-plugin-hot-dev/blob/83cd4be/src/lib/Spawn.ts#L201"}],"parentId":236}],"is":{"declaration":true},"location":{"query":"lib/Spawn.Class.Spawn","hash":"runNpmScripts"},"text":{},"parentId":200},{"id":231,"name":"spawnNpmScript","kind":2048,"kindString":"Method","flags":{"isProtected":true},"sources":[{"fileName":"src/lib/Spawn.ts","fullFileName":"/home/runner/work/typedoc-plugin-hot-dev/typedoc-plugin-hot-dev/src/lib/Spawn.ts","line":177,"character":11,"url":"https://github.com/citkane/typedoc-plugin-hot-dev/blob/83cd4be/src/lib/Spawn.ts#L177"}],"signatures":[{"id":232,"name":"spawnNpmScript","kind":4096,"kindString":"Call signature","flags":{},"parameters":[{"id":233,"name":"emitter","kind":32768,"kindString":"Parameter","flags":{},"type":{"type":"reference","id":49,"name":"HotEmitter"},"text":{}},{"id":234,"name":"controller","kind":32768,"kindString":"Parameter","flags":{},"type":{"type":"reference","name":"AbortController","qualifiedName":"AbortController","package":"typescript"},"text":{}},{"id":235,"name":"script","kind":32768,"kindString":"Parameter","flags":{},"type":{"type":"intrinsic","name":"string"},"text":{}}],"type":{"type":"reference","id":39,"name":"spawnedProcess"},"is":{"declaration":false},"location":{"query":"lib/Spawn.Spawn.Method.spawnNpmScript","hash":"spawnNpmScript.spawnNpmScript"},"text":{},"sources":[{"fileName":"src/lib/Spawn.ts","fullFileName":"/home/runner/work/typedoc-plugin-hot-dev/typedoc-plugin-hot-dev/src/lib/Spawn.ts","line":177,"character":1,"url":"https://github.com/citkane/typedoc-plugin-hot-dev/blob/83cd4be/src/lib/Spawn.ts#L177"}],"parentId":231}],"is":{"declaration":true},"location":{"query":"lib/Spawn.Class.Spawn","hash":"spawnNpmScript"},"text":{},"parentId":200},{"id":213,"name":"spawnTsDoc","kind":2048,"kindString":"Method","flags":{"isProtected":true},"sources":[{"fileName":"src/lib/Spawn.ts","fullFileName":"/home/runner/work/typedoc-plugin-hot-dev/typedoc-plugin-hot-dev/src/lib/Spawn.ts","line":95,"character":11,"url":"https://github.com/citkane/typedoc-plugin-hot-dev/blob/83cd4be/src/lib/Spawn.ts#L95"}],"signatures":[{"id":214,"name":"spawnTsDoc","kind":4096,"kindString":"Call signature","flags":{},"comment":{"summary":[{"kind":"text","text":"Spawns a disposable typedoc process using"}],"blockTags":[{"tag":"@returns","content":[]}]},"parameters":[{"id":215,"name":"emitter","kind":32768,"kindString":"Parameter","flags":{},"type":{"type":"reference","id":49,"name":"HotEmitter"},"text":{}},{"id":216,"name":"opts","kind":32768,"kindString":"Parameter","flags":{},"type":{"type":"reference","id":19,"name":"allOptions"},"text":{}},{"id":217,"name":"controller","kind":32768,"kindString":"Parameter","flags":{},"type":{"type":"reference","name":"AbortController","qualifiedName":"AbortController","package":"typescript"},"text":{}},{"id":218,"name":"command","kind":32768,"kindString":"Parameter","flags":{},"type":{"type":"intrinsic","name":"string"},"defaultValue":"'node'","text":{}},{"id":219,"name":"buildCount","kind":32768,"kindString":"Parameter","flags":{},"type":{"type":"intrinsic","name":"any"},"text":{}}],"type":{"type":"reference","id":39,"name":"spawnedProcess"},"is":{"declaration":false},"location":{"query":"lib/Spawn.Spawn.Method.spawnTsDoc","hash":"spawnTsDoc.spawnTsDoc"},"text":{"comment":"<p>Spawns a disposable typedoc process using</p>\n<h5>Returns:</h5>"},"sources":[{"fileName":"src/lib/Spawn.ts","fullFileName":"/home/runner/work/typedoc-plugin-hot-dev/typedoc-plugin-hot-dev/src/lib/Spawn.ts","line":95,"character":1,"url":"https://github.com/citkane/typedoc-plugin-hot-dev/blob/83cd4be/src/lib/Spawn.ts#L95"}],"parentId":213}],"is":{"declaration":true},"location":{"query":"lib/Spawn.Class.Spawn","hash":"spawnTsDoc"},"text":{},"parentId":200},{"id":205,"name":"spawnTscWatch","kind":2048,"kindString":"Method","flags":{"isProtected":true},"sources":[{"fileName":"src/lib/Spawn.ts","fullFileName":"/home/runner/work/typedoc-plugin-hot-dev/typedoc-plugin-hot-dev/src/lib/Spawn.ts","line":30,"character":11,"url":"https://github.com/citkane/typedoc-plugin-hot-dev/blob/83cd4be/src/lib/Spawn.ts#L30"}],"signatures":[{"id":206,"name":"spawnTscWatch","kind":4096,"kindString":"Call signature","flags":{},"comment":{"summary":[{"kind":"text","text":"Spawns a tsc process in watch mode"}],"blockTags":[{"tag":"@returns","content":[]}]},"parameters":[{"id":207,"name":"emitter","kind":32768,"kindString":"Parameter","flags":{},"type":{"type":"reference","id":49,"name":"HotEmitter"},"text":{}},{"id":208,"name":"controller","kind":32768,"kindString":"Parameter","flags":{},"type":{"type":"reference","name":"AbortController","qualifiedName":"AbortController","package":"typescript"},"text":{}},{"id":209,"name":"opts","kind":32768,"kindString":"Parameter","flags":{},"type":{"type":"reference","id":19,"name":"allOptions"},"text":{}}],"type":{"type":"reference","id":39,"name":"spawnedProcess"},"is":{"declaration":false},"location":{"query":"lib/Spawn.Spawn.Method.spawnTscWatch","hash":"spawnTscWatch.spawnTscWatch"},"text":{"comment":"<p>Spawns a tsc process in watch mode</p>\n<h5>Returns:</h5>"},"sources":[{"fileName":"src/lib/Spawn.ts","fullFileName":"/home/runner/work/typedoc-plugin-hot-dev/typedoc-plugin-hot-dev/src/lib/Spawn.ts","line":30,"character":1,"url":"https://github.com/citkane/typedoc-plugin-hot-dev/blob/83cd4be/src/lib/Spawn.ts#L30"}],"parentId":205}],"is":{"declaration":true},"location":{"query":"lib/Spawn.Class.Spawn","hash":"spawnTscWatch"},"text":{},"parentId":200},{"id":249,"name":"startWatchingFiles","kind":2048,"kindString":"Method","flags":{"isProtected":true,"isInherited":true},"sources":[{"fileName":"src/lib/Utils.ts","fullFileName":"/home/runner/work/typedoc-plugin-hot-dev/typedoc-plugin-hot-dev/src/lib/Utils.ts","line":70,"character":11,"url":"https://github.com/citkane/typedoc-plugin-hot-dev/blob/83cd4be/src/lib/Utils.ts#L70"}],"signatures":[{"id":250,"name":"startWatchingFiles","kind":4096,"kindString":"Call signature","flags":{"isInherited":true},"parameters":[{"id":251,"name":"opts","kind":32768,"kindString":"Parameter","flags":{},"type":{"type":"reference","id":19,"name":"allOptions"},"text":{}},{"id":252,"name":"emitter","kind":32768,"kindString":"Parameter","flags":{},"type":{"type":"reference","id":49,"name":"HotEmitter"},"defaultValue":"...","text":{}}],"type":{"type":"reference","name":"FSWatcher","qualifiedName":"FSWatcher","package":"chokidar"},"inheritedFrom":{"type":"reference","id":285,"name":"HotUtils.startWatchingFiles"},"is":{"declaration":false},"location":{"query":"lib/Spawn.Spawn.Method.startWatchingFiles","hash":"startWatchingFiles.startWatchingFiles"},"text":{},"sources":[{"fileName":"src/lib/Utils.ts","fullFileName":"/home/runner/work/typedoc-plugin-hot-dev/typedoc-plugin-hot-dev/src/lib/Utils.ts","line":70,"character":1,"url":"https://github.com/citkane/typedoc-plugin-hot-dev/blob/83cd4be/src/lib/Utils.ts#L70"}],"parentId":249}],"inheritedFrom":{"type":"reference","id":284,"name":"HotUtils.startWatchingFiles"},"is":{"declaration":true},"location":{"query":"lib/Spawn.Class.Spawn","hash":"startWatchingFiles"},"text":{},"parentId":200}],"groups":[{"title":"Constructors","children":[201]},{"title":"Properties","children":[204,240,241]},{"title":"Methods","children":[253,220,257,246,225,210,263,242,236,231,213,205,249]}],"sources":[{"fileName":"src/lib/Spawn.ts","fullFileName":"/home/runner/work/typedoc-plugin-hot-dev/typedoc-plugin-hot-dev/src/lib/Spawn.ts","line":17,"character":13,"url":"https://github.com/citkane/typedoc-plugin-hot-dev/blob/83cd4be/src/lib/Spawn.ts#L17"}],"extendedTypes":[{"type":"reference","id":270,"name":"HotUtils"}],"extendedBy":[{"type":"reference","id":118,"name":"Hot"}],"is":{"declaration":true},"location":{"query":"lib/Spawn.Class.Spawn","hash":""},"text":{"comment":"\n<a href=\"#creates-spawned-processes\" id=\"creates-spawned-processes\" style=\"color: inherit; text-decoration: none;\">\n  <h3>Creates spawned processes.</h3>\n</a>\n<ul>\n<li>the tsc compiler in watch mode</li>\n<li>disposable typedoc processes</li>\n</ul>\n"},"parentId":199,"hierarchy":[{"name":"HotUtils","linkId":"270","children":[{"name":"Spawn","isTarget":true,"linkId":"200","children":[{"name":"Hot","linkId":"118"}]}]}]}
